LICENSE
MANIFEST.in
README.md
README.rst
setup.cfg
setup.py
djburger/__init__.py
djburger/controllers.py
djburger/exceptions.py
djburger/mocks.py
djburger/parsers.py
djburger/renderers.py
djburger/utils.py
djburger/views.py
djburger.egg-info/PKG-INFO
djburger.egg-info/SOURCES.txt
djburger.egg-info/dependency_links.txt
djburger.egg-info/requires.txt
djburger.egg-info/top_level.txt
djburger/datastructures/__init__.py
djburger/datastructures/multidict.py
djburger/datastructures/querydict.py
djburger/validators/__init__.py
djburger/validators/bases.py
djburger/validators/constructors.py
djburger/validators/wrappers.py