Metadata-Version: 1.1
Name: djburger
Version: 0.11.1
Summary: Framework for views in big projects on Django.
Home-page: https://github.com/orsinium/djburger
Author: orsinium
Author-email: master_fess@mail.ru
License: GNU Lesser General Public License v3.0
Download-URL: https://github.com/orsinium/djburger/tarball/master
Keywords: djburger framework django contracts pre post validation
Platform: UNKNOWN
Classifier: Development Status :: 4 - Beta
Classifier: Environment :: Plugins
Classifier: Framework :: Django
Classifier: Intended Audience :: Developers
Classifier: License :: OSI Approved :: GNU Lesser General Public License v3 or later (LGPLv3+)
Classifier: Programming Language :: Python
